py_dchcaptcha/__init__.py
py_dchcaptcha-0.0.1.dist-info/METADATA
py_dchcaptcha-0.0.1.dist-info/WHEEL
py_dchcaptcha-0.0.1.dist-info/top_level.txt
py_dchcaptcha-0.0.1.dist-info/RECORD
