Metadata-Version: 2.1
Name: py_dchcaptcha
Version: 0.0.1
Summary: A wrapper for dchcaptcha.com
Author-email: Sysys242 <sysys@deobfuscate.fr>
Project-URL: Homepage, https://github.com/Sysys242/DCHcaptcha-py
Project-URL: Issues, https://github.com/Sysys242/DCHcaptcha-py/issues
Classifier: Programming Language :: Python :: 3
Classifier: License :: OSI Approved :: MIT License
Classifier: Operating System :: OS Independent
Requires-Python: >=3.8
